{
  "Lalvin": [
    {
      "name": "18-2007",
      "Nitrogen Requirement": "Low",
      "ABV Tolerance": 15,
      "LowTemp": 50,
      "High Temp": 90
    },
    {
      "name": "1895C",
      "Nitrogen Requirement": "Low",
      "ABV Tolerance": 15,
      "LowTemp": 60,
      "High Temp": 89
    },
    {
      "name": "71B",
      "Nitrogen Requirement": "Low",
      "ABV Tolerance": 14,
      "LowTemp": 59,
      "High Temp": 86
    }, 
    {
      "name": "ALCHEMY I",
      "Nitrogen Requirement": "Medium",
      "ABV Tolerance": 15.5,
      "LowTemp": 56,
      "High Temp": 61
    },
    {
      "name": "ALCHEMY II",
      "Nitrogen Requirement": "Medium",
      "ABV Tolerance": 15.5,
      "LowTemp": 56,
      "High Temp": 62
    },
    {
      "name": "ALCHEMY III",
      "Nitrogen Requirement": "Medium",
      "ABV Tolerance": 15.5,
      "LowTemp": 61,
      "High Temp": 82
    },
    {
      "name": "ALCHEMY IV",
      "Nitrogen Requirement": "Medium",
      "ABV Tolerance": 15.5,
      "LowTemp": 61,
      "High Temp": 82
    },
    {
      "name": "BA11",
      "Nitrogen Requirement": "High",
      "ABV Tolerance": 16,
      "LowTemp": 59,
      "High Temp": 77
    }, 
    {
      "name": "BDX",
      "Nitrogen Requirement": "Medium",
      "ABV Tolerance": 16,
      "LowTemp": 64,
      "High Temp": 86
    },
    {
      "name": "BM 45",
      "Nitrogen Requirement": "High",
      "ABV Tolerance": 15,
      "LowTemp": 64,
      "High Temp": 82
    },
    {
      "name": "BM 4x4",
      "Nitrogen Requirement": "High",
      "ABV Tolerance": 16,
      "LowTemp": 64,
      "High Temp": 82
    },
    {
      "name": "BRL97",
      "Nitrogen Requirement": "Medium",
      "ABV Tolerance": 16,
      "LowTemp": 62,
      "High Temp": 85
    },  
    {
      "name": "C",
      "Nitrogen Requirement": "Low",
      "ABV Tolerance": 17,
      "LowTemp": 59,
      "High Temp": 86
    },
    {
      "name": "CLOS",
      "Nitrogen Requirement": "Medium",
      "ABV Tolerance": 17,
      "LowTemp": 57,
      "High Temp": 90
    }
  ],
  "Mangrove Jack": [
    {
      "name": "AW4",
      "Nitrogen Requirement": "Low",
      "ABV Tolerance": 14,
      "LowTemp": 61,
      "High Temp": 75
    },
    {
      "name": "BV7",
      "Nitrogen Requirement": "Low",
      "ABV Tolerance": 14,
      "LowTemp": 57,
      "High Temp": 82
    },
    {
      "name": "CL23",
      "Nitrogen Requirement": "Low",
      "ABV Tolerance": 18,
      "LowTemp": 57,
      "High Temp": 90
    }
  ],
  "Red Star": [
    {
      "name": "Cotes des Blanc",
      "Nitrogen Requirement": "Medium",
      "ABV Tolerance": "12-14",
      "LowTemp": 64,
      "High Temp": 86
    }
  ],
  "Other": []
}